google_benchmark/__init__.py
google_benchmark/_benchmark.pyd
google_benchmark/_benchmark.pyi
google_benchmark/example.py
google_benchmark/py.typed
google_benchmark-1.9.4.dist-info/licenses/AUTHORS
google_benchmark-1.9.4.dist-info/licenses/LICENSE
google_benchmark-1.9.4.dist-info/METADATA
google_benchmark-1.9.4.dist-info/WHEEL
google_benchmark-1.9.4.dist-info/top_level.txt
google_benchmark-1.9.4.dist-info/RECORD
