Metadata-Version: 2.4
Name: google_benchmark
Version: 1.9.4
Summary: A library to benchmark code snippets.
Author-email: Google <benchmark-discuss@googlegroups.com>
License: 
Project-URL: Homepage, https://github.com/google/benchmark
Project-URL: Documentation, https://github.com/google/benchmark/tree/main/docs
Project-URL: Repository, https://github.com/google/benchmark.git
Project-URL: Discord, https://discord.gg/cz7UX7wKC2
Keywords: benchmark
Classifier: Development Status :: 4 - Beta
Classifier: Intended Audience :: Developers
Classifier: Intended Audience :: Science/Research
Classifier: License :: OSI Approved :: Apache Software License
Classifier: Programming Language :: Python :: 3.10
Classifier: Programming Language :: Python :: 3.11
Classifier: Programming Language :: Python :: 3.12
Classifier: Topic :: Software Development :: Testing
Classifier: Topic :: System :: Benchmark
Requires-Python: >=3.10
License-File: LICENSE
License-File: AUTHORS
Requires-Dist: absl-py>=0.7.1
Provides-Extra: dev
Requires-Dist: pre-commit>=3.3.3; extra == "dev"
Dynamic: license-file
